doctran/__init__.py
doctran/doctran.py
doctran/transformers/__init__.py
doctran/transformers/transformers.py
doctran-0.0.13.dist-info/LICENSE
doctran-0.0.13.dist-info/METADATA
doctran-0.0.13.dist-info/WHEEL
doctran-0.0.13.dist-info/RECORD
