Metadata-Version: 2.1
Name: doctran
Version: 0.0.13
Summary: Document transformation framework for vector based retrieval
Author: Jason Fan
Author-email: jason.wc.fan@gmail.com
Requires-Python: >=3.8.1,<4.0.0
Classifier: Programming Language :: Python :: 3
Classifier: Programming Language :: Python :: 3.9
Classifier: Programming Language :: Python :: 3.10
Classifier: Programming Language :: Python :: 3.11
Requires-Dist: lxml (>=4.9.2,<5.0.0)
Requires-Dist: openai (>=0.27.8,<0.28.0)
Requires-Dist: presidio-analyzer (>=2.2.33,<3.0.0)
Requires-Dist: presidio-anonymizer (>=2.2.33,<3.0.0)
Requires-Dist: pydantic (>=1.10.9,<2.0.0)
Requires-Dist: spacy (>=3.5.4,<4.0.0)
Requires-Dist: tiktoken (>=0.5.0,<0.6.0)
